feedparser/__init__.py
feedparser/api.py
feedparser/encodings.py
feedparser/exceptions.py
feedparser/html.py
feedparser/http.py
feedparser/mixin.py
feedparser/sanitizer.py
feedparser/sgml.py
feedparser/urls.py
feedparser/util.py
feedparser/datetimes/__init__.py
feedparser/datetimes/asctime.py
feedparser/datetimes/greek.py
feedparser/datetimes/hungarian.py
feedparser/datetimes/iso8601.py
feedparser/datetimes/korean.py
feedparser/datetimes/perforce.py
feedparser/datetimes/rfc822.py
feedparser/datetimes/w3dtf.py
feedparser/namespaces/__init__.py
feedparser/namespaces/_base.py
feedparser/namespaces/admin.py
feedparser/namespaces/cc.py
feedparser/namespaces/dc.py
feedparser/namespaces/georss.py
feedparser/namespaces/itunes.py
feedparser/namespaces/mediarss.py
feedparser/namespaces/psc.py
feedparser/parsers/__init__.py
feedparser/parsers/loose.py
feedparser/parsers/strict.py
forkparser-6.1.0.dist-info/DESCRIPTION.rst
forkparser-6.1.0.dist-info/METADATA
forkparser-6.1.0.dist-info/RECORD
forkparser-6.1.0.dist-info/WHEEL
forkparser-6.1.0.dist-info/metadata.json
forkparser-6.1.0.dist-info/top_level.txt
