Metadata-Version: 2.0
Name: forkparser
Version: 6.1.0
Summary: A hopefully temporary fork of Universal Feed Parser, which handles RSS 0.9x, RSS 1.0, RSS 2.0, CDF, Atom 0.3, and Atom 1.0 feeds
Home-page: https://github.com/twm/feedparser
Author: Tom Most
Author-email: forkparser@freecog.net
License: UNKNOWN
Download-URL: https://pypi.python.org/pypi/forkparser
Keywords: atom,cdf,feed,parser,rdf,rss
Platform: POSIX
Platform: Windows
Classifier: Development Status :: 5 - Production/Stable
Classifier: Intended Audience :: Developers
Classifier: License :: OSI Approved
Classifier: Operating System :: OS Independent
Classifier: Programming Language :: Python
Classifier: Programming Language :: Python :: 2
Classifier: Programming Language :: Python :: 2.7
Classifier: Programming Language :: Python :: 3
Classifier: Programming Language :: Python :: 3.2
Classifier: Programming Language :: Python :: 3.3
Classifier: Programming Language :: Python :: 3.4
Classifier: Programming Language :: Python :: 3.5
Classifier: Topic :: Software Development :: Libraries :: Python Modules
Classifier: Topic :: Text Processing :: Markup :: XML
Requires-Dist: sgmllib3k; python_version >= "3.0"
